{"nodes": [{"id": "c_projects_posapp_posapp_core_entities_holdsale_cs", "label": "HoldSale.cs", "file_type": "code", "source_file": "POSApp.Core/Entities/HoldSale.cs", "source_location": "L1"}, {"id": "entities_holdsale_posapp_core_entities", "label": "POSApp.Core.Entities", "file_type": "code", "source_file": "POSApp.Core/Entities/HoldSale.cs", "source_location": "L1"}, {"id": "entities_holdsale_holdsale", "label": "HoldSale", "file_type": "code", "source_file": "POSApp.Core/Entities/HoldSale.cs", "source_location": "L3"}], "edges": [{"source": "c_projects_posapp_posapp_core_entities_holdsale_cs", "target": "entities_holdsale_posapp_core_entities", "relation": "contains", "confidence": "EXTRACTED", "source_file": "POSApp.Core/Entities/HoldSale.cs", "source_location": "L1", "weight": 1.0}, {"source": "c_projects_posapp_posapp_core_entities_holdsale_cs", "target": "entities_holdsale_holdsale", "relation": "contains", "confidence": "EXTRACTED", "source_file": "POSApp.Core/Entities/HoldSale.cs", "source_location": "L3", "weight": 1.0}], "raw_calls": []}